.travis.yml
MANIFEST.in
NOTICE.txt
README.rst
bootstrap.py
buildout.cfg
edrndmcc.appserver.sublime-project
setup.py
travis.cfg
docs/HISTORY.txt
docs/INSTALL.txt
docs/LICENSE.txt
edrndmcc/__init__.py
edrndmcc.appserver.egg-info/PKG-INFO
edrndmcc.appserver.egg-info/SOURCES.txt
edrndmcc.appserver.egg-info/dependency_links.txt
edrndmcc.appserver.egg-info/entry_points.txt
edrndmcc.appserver.egg-info/namespace_packages.txt
edrndmcc.appserver.egg-info/not-zip-safe
edrndmcc.appserver.egg-info/requires.txt
edrndmcc.appserver.egg-info/top_level.txt
edrndmcc/appserver/__init__.py
edrndmcc/appserver/configure.zcml
edrndmcc/appserver/setuphandlers.py
edrndmcc/appserver/testing.py
edrndmcc/appserver/upgrades.py
edrndmcc/appserver/upgrades.zcml
edrndmcc/appserver/data/staff-photographs.zexp
edrndmcc/appserver/profiles/default/edrndmcc.appserver.marker.txt
edrndmcc/appserver/profiles/default/metadata.xml
edrndmcc/appserver/profiles/default/properties.xml
edrndmcc/appserver/profiles/default/viewlets.xml
edrndmcc/appserver/profiles/default/structure/.objects
edrndmcc/appserver/profiles/default/structure/.properties
edrndmcc/appserver/profiles/default/structure/front-page
edrndmcc/appserver/profiles/summarizer/edrnsummarizer.appserver.marker.txt
edrndmcc/appserver/profiles/summarizer/metadata.xml
edrndmcc/appserver/profiles/summarizer/properties.xml
edrndmcc/appserver/profiles/summarizer/viewlets.xml
edrndmcc/appserver/profiles/summarizer/structure/.objects
edrndmcc/appserver/profiles/summarizer/structure/.properties
edrndmcc/appserver/profiles/summarizer/structure/front-page
edrndmcc/appserver/tests/__init__.py
edrndmcc/appserver/tests/test_setup.py
parts/omelette/edrndmcc/appserver/__init__.py
parts/omelette/edrndmcc/appserver/configure.zcml
parts/omelette/edrndmcc/appserver/setuphandlers.py
parts/omelette/edrndmcc/appserver/testing.py
parts/omelette/edrndmcc/appserver/upgrades.py
parts/omelette/edrndmcc/appserver/upgrades.zcml
parts/omelette/edrndmcc/appserver/data/staff-photographs.zexp
parts/omelette/edrndmcc/appserver/profiles/default/edrndmcc.appserver.marker.txt
parts/omelette/edrndmcc/appserver/profiles/default/metadata.xml
parts/omelette/edrndmcc/appserver/profiles/default/properties.xml
parts/omelette/edrndmcc/appserver/profiles/default/viewlets.xml
