Metadata-Version: 1.1
Name: edrndmcc.appserver
Version: 1.2.5
Summary: EDRN DMCC Application Server policy
Home-page: https://github.com/EDRN/edrndmcc.appserver
Author: Sean Kelly
Author-email: sean.kelly@jpl.nasa.gov
License: ALv2
Keywords: web policy zope plone jpl nasa caltech edrn cancer detection appserver application server
Platform: UNKNOWN
Classifier: Development Status :: 4 - Beta
Classifier: Environment :: Web Environment
Classifier: Framework :: Plone
Classifier: Intended Audience :: Healthcare Industry
Classifier: Intended Audience :: Science/Research
Classifier: License :: OSI Approved :: Apache Software License
Classifier: Operating System :: OS Independent
Classifier: Programming Language :: Python
Classifier: Topic :: Internet :: WWW/HTTP
Classifier: Topic :: Scientific/Engineering :: Bio-Informatics
Classifier: Topic :: Software Development :: Libraries :: Python Modules
